festivus/__init__.py
festivus/finder.py
festivus/data/festivals.json
festivus-0.1.0.dist-info/LICENSE
festivus-0.1.0.dist-info/METADATA
festivus-0.1.0.dist-info/WHEEL
festivus-0.1.0.dist-info/top_level.txt
festivus-0.1.0.dist-info/RECORD
