Metadata-Version: 2.1
Name: festivus
Version: 0.1.0
Summary: A simple Indian festival finder package by month, region, religion, and date
Home-page: https://github.com/yourusername/festivus
Author: Avinash Parab
Author-email: your_email@example.com
License: UNKNOWN
Platform: UNKNOWN
Classifier: Programming Language :: Python :: 3
Classifier: License :: OSI Approved :: MIT License
Classifier: Operating System :: OS Independent
Requires-Python: >=3.6
License-File: LICENSE
